signal_envelope/__init__.py
signal_envelope/envelope.dll
signal_envelope/envelope.py
signal_envelope-1.3.dist-info/LICENSE
signal_envelope-1.3.dist-info/METADATA
signal_envelope-1.3.dist-info/WHEEL
signal_envelope-1.3.dist-info/top_level.txt
signal_envelope-1.3.dist-info/RECORD
