Metadata-Version: 2.1
Name: signal-envelope
Version: 1.3
Summary: Extracts the temporal envelope of a digital signal
Home-page: https://github.com/tesserato/envelope
Author: Carlos Tarjano
Author-email: tesserato@hotmail.com
License: MIT
Platform: UNKNOWN
Classifier: License :: OSI Approved :: MIT License
Classifier: Programming Language :: Python :: 3
Requires-Dist: numpy
